[
    {
        "title": "aviman bengoli",
        "url": "https://www.youtube.com/embed/yaRCyb8VK84?si=pOumGLPVvp-l_SaU",
        "category": "movie",
        "tags": ["Adventure"],
        "thambnail": "https://i.ibb.co/QH39zs9/MV5-BYm-Q3-NDhj-MTkt-ZGQ0-Yy00-N2-Rm-LTll-NGMt-Njc4-OTlm-YWNh-ZDg0-Xk-Ey-Xk-Fqc-Gde-QXVy-OTgz-MDgy-O.jpg",
        "description": "aviman bengoli full hd movies|Jeet|shubhasree|sayontika|full action movies",
        "rating": "4",
        "language": "bangla",
        "hero": "Jeet|shubhasree|sayontika",
        "date": "2023-08-21"
    },
    {
        "title": "Daal Baati Churma",
        "url": "https://www.youtube.com/embed/_B4sqC9sRTs?si=1iKojkJfqkiY2C8l",
        "category": "movie",
        "tags": ["Comedy"],
        "thambnail": "https://i.ibb.co/DfzBJ4n/8fd18b75e17ca253cef303a83d3c9a10167098399006249-original.jpg",
        "description": "Daal Baati Churma bengali full Movie | Bonny | Koushani | Full HD | New Bengali Movie",
        "rating": "5",
        "language": "bangla",
        "hero": "Bonny | Koushani",
        "date": "2023-08-21"
    },
    {
        "title": "JIO PAGLA FULL MOVIE",
        "url": "https://www.youtube.com/embed/4oNEr6m8JZA?si=l4ITncz8S4cV4bbj",
        "category": "movie",
        "tags": ["Comedy"],
        "thambnail": "https://i.ibb.co/zP09ycL/maxresdefault-9.jpg",
        "description": "JIO PAGLA FULL MOVIE | NEW BENGALI MOVIE | LOVE STORIES | COMEDY MOVIE | KOLKATA MOVIE",
        "rating": "5",
        "language": "bangla",
        "hero": "Bonny | Koushani",
        "date": "2023-08-21"
    },
    {
        "title": "The Stolen Princess",
        "url": "https://www.youtube.com/embed/YxrHSsREWOU?si=LpTVM4xrPWv6v88K",
        "category": "movie",
        "tags": ["Kids"],
        "thambnail": "https://i.ibb.co/jzHr6vZ/MV5-BOTUy-Ym-Zh-Nzkt-NGJi-OS00-NDZl-LWJm-Y2-Mt-YTMz-Zj-M5-NGZm-OGVh-Xk-Ey-Xk-Fqc-Gde-QXVy-ODQw-NTU3.jpg",
        "description": "The Stolen Princess Full Movie - Bengali Dubbed Latest Hollywood Movie - Animation Movie",
        "rating": "4",
        "language": "bangla",
        "hero": "Anima hero",
        "date": "2023-08-21"
    },
    {
        "title": "The House Eif Full Advencer Magical Movie",
        "url": "https://www.youtube.com/embed/4BPOYgSu8h8?si=7KyT3AqRE500P--z",
        "category": "movie",
        "tags": ["Adventure"],
        "thambnail": "https://i.ibb.co/YZ8nqYD/the-house-elf-IOd-Hn-WU.jpg",
        "description": "The House Eif Full Advencer Magical Movie || Hindi Dubbed || Hollywood Full Action Movie",
        "rating": "3",
        "language": "hindi",
        "hero": "marina | javed",
        "date": "2023-08-21"
    },
    {
        "title": "The Wild Life",
        "url": "https://www.youtube.com/embed/osY8CQ7XESA?si=o7iuK9dooRngRTCw",
        "category": "movie",
        "tags": ["Kids"],
        "thambnail": "https://i.ibb.co/3rvsrW0/MV5-BMj-A4-OTE0-Mj-Aw-Nl5-BMl5-Ban-Bn-Xk-Ft-ZTgw-Mj-Y4-Mzg2-OTE-V1-FMjpg-UX1000.jpg",
        "description": "The Wild Life (2016) full movie in Hindi || Robisnon Crusoe",
        "rating": "5",
        "language": "hindi",
        "hero": "Robisnon Crusoe",
        "date": "2023-08-21"
    },
    {
        "title": "हैलोवीन - चुड़ैल और ",
        "url": "https://www.youtube.com/embed/IdDFD3h1P-s?si=LTxeud2agT0QzStc",
        "category": "movie",
        "tags": ["Horror"],
        "thambnail": "https://i.ibb.co/XFyQMWN/maxresdefault-10.jpg",
        "description": "Halloween Special Horor Movie",
        "rating": "4",
        "language": "hindi",
        "hero": "karan",
        "date": "2023-08-21"
    },
    {
        "title": "Welcome To The Jungle",
        "url": "https://www.youtube.com/embed/hLpJIsPhErE?si=Ax0rRAN6mh81zG9J",
        "category": "movie",
        "tags": ["Comedy"],
        "thambnail": "https://i.ibb.co/4dJsmMM/story-1693289114.jpg",
        "description": "Welcome To The Jungle New Full Hindi Comedy Movie 2024 ",
        "rating": "4",
        "language": "hindi",
        "hero": "Akshay Kumar, Raveena Tandon, Disha Patani",
        "date": "2023-08-21"
    },
    {
        "title": "電影《校花詭異事件》",
        "url": "https://www.youtube.com/embed/Qdc4Iba-OEs?si=H58MfAACkyrs5T3l",
        "category": "movie",
        "tags": ["Horror"],
        "thambnail": "https://i.ibb.co/yW0g81n/maxresdefault-11.jpg",
        "description": "電影《校花詭異事件》“人鬼情未了”的感人愛情故事 | Horor & Love film 恐怖愛情片 HD",
        "rating": "5",
        "language": "korean",
        "hero": "恐怖愛情片",
        "date": "2023-08-21"
    },
    {
        "title": "Lost in Apocalypse",
        "url": "https://www.youtube.com/embed/tYvHdOAMStI?si=juQ1BikpEJ6QE-KQ",
        "category": "movie",
        "tags": ["Adventure"],
        "thambnail": "https://i.ibb.co/ydynSkb/apocalypse-poster-400x650.jpg",
        "description": "Lost in Apocalypse | Zombies | Virus | Suspense",
        "rating": "5",
        "language": "korean",
        "hero": "Youn | sakura",
        "date": "2023-08-21"
    },
    {
        "title": "Psychic School Wars",
        "url": "https://www.youtube.com/embed/y0y2ya6PMC8?si=Me8Ioj0UlXtUxDaB",
        "category": "movie",
        "tags": ["Kids"],
        "thambnail": "https://i.ibb.co/pLNRmWc/Psychic-School-Wars-Key-Visual.jpg",
        "description": "Anime movie: Psychic School Wars [full movie, eng sub]",
        "rating": "5",
        "language": "korean",
        "hero": "Youn | sakura",
        "date": "2023-08-21"
    },
    {
        "title": "Hello Mr. Billionaire",
        "url": "https://www.youtube.com/embed/F2udS8TlLak?si=xWmiUfrBfuv07Q4c",
        "category": "movie",
        "tags": ["Comedy"],
        "thambnail": "https://i.ibb.co/NS0JRjN/p18568452-v-v8-aa.jpg",
        "description": "Hello Mr. Billionaire [full movie, eng sub]",
        "rating": "4",
        "language": "korean",
        "hero": "Billionaire",
        "date": "2023-08-21"
    },
    {
        "title": "SIJJIN FULL MOVIE",
        "url": "https://www.youtube.com/embed/eVlrsz4A9eo?si=mJmFyqUHVQucvBfM",
        "category": "movie",
        "tags": ["Horror"],
        "thambnail": "https://i.ibb.co/hDDL6fY/MV5-BYWU2-Yj-E0-Zjct-Nm-Q1-Mi00-NGVj-LTlk-NGEt-Nz-Ji-MTYx-NTE2-NTdh-Xk-Ey-Xk-Fqc-Gde-QXVy-MTEz-MTI1.jpg",
        "description": "SIJJIN FULL MOVIE || Film Horor Indonesia Terbaru 2023 || FULL MOVIE",
        "rating": "5",
        "language": "Indonesian",
        "hero": "Billionaire",
        "date": "2023-08-21"
    },
    {
        "title": "Kena: Bridge of Spirits",
        "url": "https://www.youtube.com/embed/28CIeC8cZks?si=RHQkHAD1S0H6dtKd",
        "category": "movie",
        "tags": ["Kids"],
        "thambnail": "https://i.ibb.co/MPv0pVq/maxresdefault-12.jpg",
        "description": "Kena: Bridge of Spirits Full Animation Movie [1080p HD 60FPS]",
        "rating": "5",
        "language": "Indonesian",
        "hero": "kena",
        "date": "2023-08-21"
    },
    {
        "title": "Amazon Queen",
        "url": "https://www.youtube.com/embed/SDzsm515jak?si=_Xq1yfpIw1Lppmea",
        "category": "movie",
        "tags": ["Adventure"],
        "thambnail": "https://i.ibb.co/dPnhCZ6/MV5-BOWUw-Mz-Ew-ZDIt-ZTMw-Ni00-MTBj-LTk0-Zj-At-Ym-M1-Nj-Az-YWQ0-MGE1-Xk-Ey-Xk-Fqc-Gde-QXVy-Nz-Iy-MTU.jpg",
        "description": "Amazon Queen - An idyllic riverboat cruise through the exotic Amazon rainforest becomes a nightmare for the crew and passengers ",
        "rating": "5",
        "language": "Indonesian",
        "hero": "Carson Grant, Nick Dreselly",
        "date": "2023-08-21"
    },
    {
        "title": "PATIENT SEVEN",
        "url": "https://www.youtube.com/embed/ztlspLwdgts?si=7fGI4ZcmSjM4sE15",
        "category": "movie",
        "tags": ["Horror"],
        "thambnail": "https://i.ibb.co/yPwYSvQ/maxresdefault-13.jpg",
        "description": "A renowned psychiatrist has selected six mental patients to interview as part of the research for his new book.",
        "rating": "3",
        "language": "Japan",
        "hero": "Evaded | Visitant",
        "date": "2023-08-21"
    },
    {
        "title": "grave of the fireflies full movie",
        "url": "https://www.youtube.com/embed/UwMbxoG8ZV0?si=RvoLl4BjbQ925r0P",
        "category": "movie",
        "tags": ["Kids"],
        "thambnail": "https://i.ibb.co/MDYcssn/p158931-p-v10-aa.jpg",
        "description": "n the aftermath of a World War II bombing, two orphaned children struggle to survive in the Japanese countryside",
        "rating": "3",
        "language": "Japan",
        "hero": "Hotaru",
        "date": "2023-08-21"
    },
    {
        "title": "HURRICANE",
        "url": "https://www.youtube.com/embed/rLVTeUzOoto?si=9R_2LcYfSKeUr2iO",
        "category": "movie",
        "tags": ["Adventure"],
        "thambnail": "https://i.ibb.co/C9DQct0/mqdefault.jpg",
        "description": "n the aftermath of a World War II bombing, two orphaned children struggle to survive in the Japanese countryside",
        "rating": "4",
        "language": "hindi",
        "hero": "Hotaru",
        "date": "2023-08-21"
    },
    {
        "title": "ReLIFE",
        "url": "https://www.youtube.com/embed/DLKjmuAq3k8?si=WWNxg7NhKuIX6WVm",
        "category": "movie",
        "tags": ["Comedy"],
        "thambnail": "https://i.ibb.co/qxbP7v5/77279.jpg",
        "description": "ReLIFE | Full Japanese Romantic Movie",
        "rating": "3",
        "language": "Japan",
        "hero": "Taishi Nakagawa",
        "date": "2023-08-21"
    },
    {
        "title": "Beauty And The Beast (2009)",
        "url": "https://www.youtube.com/embed/yp8PHybyHsc?si=Botys2GUO8a2424n",
        "category": "movie",
        "tags": ["Adventure"],
        "thambnail": "https://i.ibb.co/2qQ7002/Beauty-and-the-Beast-2017-movie-poster-e1490633235298.jpg",
        "description": "Beauty And The Beast (2009) | English Fantasy Film | Estella Warren, Rhett Giles",
        "rating": "5",
        "language": "hindi",
        "hero": "Estella Warren, Victor Parascos, Vanessa Gray",
        "date": "2023-08-21"
    },
    {
        "title": "Wish Dragon (2021)",
        "url": "https://www.youtube.com/embed/ch-LNHdFrok?si=1aU_lZFKHCDuPm83",
        "category": "movie",
        "tags": ["Comedy"],
        "thambnail": "https://i.ibb.co/2y1Xk2N/Wish-Dragon-972181879-large.jpg",
        "description": "In Sony Pictures Animation's Wish Dragon, Din, a working-class college student with big dreams but small means,",
        "rating": "5",
        "language": "hindi",
        "hero": "Estella Warren, Vanessa Gray",
        "date": "2023-08-21"
    },
    {
        "title": "Ice Age Full movie",
        "url": "https://www.youtube.com/embed/t-u1PyUXTjA?si=Cv_BqDI2L1AR2sF2",
        "category": "movie",
        "tags": ["Kids"],
        "thambnail": "https://i.ibb.co/ChNm2kZ/bb83145a-2333-4558-889c-6f6ed0671d88.jpg",
        "description": "In Sony Pictures Animation's Wish Dragon, Din, a working-class college student with big dreams but small means,",
        "rating": "5",
        "language": "korean",
        "hero": " Vanessa Gray",
        "date": "2023-08-21"
    },
    {
        "title": "USHIRO NO SHOUMEN",
        "url": "https://www.youtube.com/embed/WNzAz6EMJbg?si=mYABZ4C4wb4tYAHx",
        "category": "movie",
        "tags": ["Kids"],
        "thambnail": "https://i.ibb.co/Jc2BpSW/0dcfe3c2c4aac937273d5563ca9a029753f1acb6.jpg",
        "description": "Japan anime movie Din, a working-class college student with big dreams but small means,",
        "rating": "3",
        "language": "Japan",
        "hero": "sakura iclelan",
        "date": "2023-08-21"
    },
    {
        "title": "Grasshopper (2015)",
        "url": "https://www.youtube.com/embed/i301EFFUU0M?si=OTTcCe2dNF5s0pxP",
        "category": "movie",
        "tags": ["Adventure"],
        "thambnail": "https://i.ibb.co/W6jZzpw/MV5-BZDg2-Nj-Zh-Mz-Yt-NWY3-NS00-M2-Uy-LTg1-YTMt-Zm-Iz-NDY5-ZTBk-MTg2-Xk-Ey-Xk-Fqc-Gde-QXVy-MTk3-NTc0.jpg",
        "description": "Suzuki is a former middle school teacher. His girlfriend was killed, which led him to quit his job and attempt to take revenge on her murderer. ",
        "rating": "3",
        "language": "Japan",
        "hero": "sakura iclelan",
        "date": "2023-08-21"
    },
    {
        "title": "My boss my teacher",
        "url": "https://www.youtube.com/embed/xvDzYcfgdig?si=5_N-z3sPzG3zpzCN",
        "category": "movie",
        "tags": ["Comedy"],
        "thambnail": "https://i.ibb.co/kHMP0Tr/MV5-BMTY5-MDU5-Nj-Iz-OF5-BMl5-Ban-Bn-Xk-Ft-ZTgw-NTY5-ODc1-Mj-E-V1-FMjpg-UX1000.jpg",
        "description": "My boss my teacher His girlfriend was killed, which led him to quit his job and attempt to take revenge on her murderer. ",
        "rating": "3",
        "language": "korean",
        "hero": "Suzuki",
        "date": "2023-08-21"
    },
    {
        "title": "Bad Cop - A Kung Fu Police Girl",
        "url": "https://www.youtube.com/embed/EtruqVFNiiY?si=ohuWF6bpEGwdx3KD",
        "category": "movie",
        "tags": ["Adventure"],
        "thambnail": "https://i.ibb.co/wLHF61s/69b6d6823958574f8b53dad4b80d46399892d52986b64f25e75406f16aad0b0e.jpg",
        "description": "The Campus Love & Action Movie Bad Cop is about a defiant cop girl Yang Yang who is sent to a campus as an undercover agent. ",
        "rating": "4",
        "language": "korean",
        "hero": "Suzuki",
        "date": "2023-08-21"
    },
    {
        "title": "HOUSEFULL 3 ",
        "url": "https://www.youtube.com/embed/JbvQbcTogT4?si=1fCrrkUljkatYUVB",
        "category": "movie",
        "tags": ["Comedy"],
        "thambnail": "https://i.ibb.co/Dw0Q8Gy/Housefull-3-movie-poster.jpg",
        "description": "Presenting Superhit Blockbuster Bollywood Movie (Full Hindi Movie, हिंदी कॉमेडी मूवी, बॉलीवुड मूवी) HOUSEFULL 3",
        "rating": "3",
        "language": "hindi",
        "hero": "Akshay Kumar, Abhishek Bachchan, Riteish Deshmukh",
        "date": "2023-08-21"
    },
    {
        "title": "fighter movie",
        "url": "https://www.youtube.com/embed/F5GY-wSno6c?si=-PTMOQ0HNW5QbOQU",
        "category": "movie",
        "tags": ["Adventure"],
        "thambnail": "https://i.ibb.co/F0QSNDk/MV5-BMDgx-YTI1-ODMt-NGFh-NC00-ZWRk-LWE4-Yjkt-ZGI5-NTlm-Njdm-MDYx-Xk-Ey-Xk-Fqc-Gde-QXVy-MTUz-NTgz-Nz.jpg",
        "description": "Presenting Superhit Blockbuster Bollywood Movie (Full Hindi Movie, हिंदी कॉमेडी मूवी, बॉलीवुड मूवी) HOUSEFULL 3",
        "rating": "4",
        "language": "hindi",
        "hero": "Akshay Kumar, Abhishek Bachchan, Riteish Deshmukh",
        "date": "2023-08-21"
    },
    {
        "title": "Big Fish and Begonia",
        "url": "https://www.youtube.com/embed/F5GY-wSno6c?si=-PTMOQ0HNW5QbOQU",
        "category": "movie",
        "tags": ["Kids"],
        "thambnail": "https://i.ibb.co/1T23yzj/2ba952ee8554456ca8bf3ad979274c2a.jpg",
        "description": "It contains deep meanings, tapping into Chinese Philosophies.",
        "rating": "5",
        "language": "Japan",
        "hero": "begonia",
        "date": "2023-08-21"
    },
    {
        "title": "The Haunted Hotel",
        "url": "https://www.youtube.com/embed/Y9Eho1PkFNY?si=M-JtJ7DNK0L7_gDo",
        "category": "movie",
        "tags": ["Horror"],
        "thambnail": "https://i.ibb.co/wwDqMSj/513-E0-W6f4k-L.jpg",
        "description": "The Haunted Hotel - Eight tales of ghostly encounters through the decades, manifesting amid the ruins of a once grand English hotel.",
        "rating": "5",
        "language": "Japan",
        "hero": "Hugh Fraser, Reece Ritchie, Rob Jarvis",
        "date": "2023-08-21"
    }
]